{
   "template":{
      "description":"This template shows a basic configuration of the GetMongo and PutMongo processors. This template assumes you have a mongo db instance running with a test db and restaurant collection within test.",
      "name":"MongoDB Get and Put Example",
      "snippet":{
         "connections":[
            {
               "id":"0dac1de2-4175-4184-aff6-e5289fc8c98f",
               "parentGroupId":"36fe07f4-72eb-43da-b86e-64277d3502e1",
               "backPressureDataSizeThreshold":"0 MB",
               "backPressureObjectThreshold":"0",
               "destination":{
                  "groupId":"36fe07f4-72eb-43da-b86e-64277d3502e1",
                  "id":"41e56cba-c491-4681-bbff-3b789a2a47cd",
                  "type":"PROCESSOR"
               },
               "flowFileExpiration":"0 sec",
               "labelIndex":"1",
               "name":"",
               "selectedRelationships":"failure",
               "source":{
                  "groupId":"36fe07f4-72eb-43da-b86e-64277d3502e1",
                  "id":"3fa515a3-fa52-47b3-85ef-8baceff8d172",
                  "type":"PROCESSOR"
               },
               "zIndex":"0"
            },
            {
               "id":"ef9182fa-9d03-4fdc-b4f1-4b4ace587c46",
               "parentGroupId":"36fe07f4-72eb-43da-b86e-64277d3502e1",
               "backPressureDataSizeThreshold":"0 MB",
               "backPressureObjectThreshold":"0",
               "destination":{
                  "groupId":"36fe07f4-72eb-43da-b86e-64277d3502e1",
                  "id":"3fa515a3-fa52-47b3-85ef-8baceff8d172",
                  "type":"PROCESSOR"
               },
               "flowFileExpiration":"0 sec",
               "labelIndex":"1",
               "name":"",
               "selectedRelationships":"success",
               "source":{
                  "groupId":"36fe07f4-72eb-43da-b86e-64277d3502e1",
                  "id":"89707d29-fd48-4fb4-8a28-a3b7c38af969",
                  "type":"PROCESSOR"
               },
               "zIndex":"0"
            },
            {
               "id":"2cfed027-eb8f-4096-9054-c18308bfdc5f",
               "parentGroupId":"36fe07f4-72eb-43da-b86e-64277d3502e1",
               "backPressureDataSizeThreshold":"0 MB",
               "backPressureObjectThreshold":"0",
               "destination":{
                  "groupId":"36fe07f4-72eb-43da-b86e-64277d3502e1",
                  "id":"fe80dab5-e13f-4af2-a9d3-507952a7516c",
                  "type":"PROCESSOR"
               },
               "flowFileExpiration":"0 sec",
               "labelIndex":"1",
               "name":"",
               "selectedRelationships":"success",
               "source":{
                  "groupId":"36fe07f4-72eb-43da-b86e-64277d3502e1",
                  "id":"50706ba6-a16f-4efa-91cd-5faacf3590d5",
                  "type":"PROCESSOR"
               },
               "zIndex":"0"
            },
            {
               "id":"83e5f373-e369-41fa-ad73-f19af64d84df",
               "parentGroupId":"36fe07f4-72eb-43da-b86e-64277d3502e1",
               "backPressureDataSizeThreshold":"0 MB",
               "backPressureObjectThreshold":"0",
               "destination":{
                  "groupId":"36fe07f4-72eb-43da-b86e-64277d3502e1",
                  "id":"89707d29-fd48-4fb4-8a28-a3b7c38af969",
                  "type":"PROCESSOR"
               },
               "flowFileExpiration":"0 sec",
               "labelIndex":"1",
               "name":"",
               "selectedRelationships":"success",
               "source":{
                  "groupId":"36fe07f4-72eb-43da-b86e-64277d3502e1",
                  "id":"c6251f06-f526-4f07-abfb-9f5e62a8f38b",
                  "type":"PROCESSOR"
               },
               "zIndex":"0"
            },
            {
               "id":"589fffbf-4c21-4833-a77f-22533d63732b",
               "parentGroupId":"36fe07f4-72eb-43da-b86e-64277d3502e1",
               "backPressureDataSizeThreshold":"0 MB",
               "backPressureObjectThreshold":"0",
               "destination":{
                  "groupId":"36fe07f4-72eb-43da-b86e-64277d3502e1",
                  "id":"cf620c13-da2e-4a58-9f3f-03540ec4e4a8",
                  "type":"PROCESSOR"
               },
               "flowFileExpiration":"0 sec",
               "labelIndex":"1",
               "name":"",
               "selectedRelationships":"success",
               "source":{
                  "groupId":"36fe07f4-72eb-43da-b86e-64277d3502e1",
                  "id":"3fa515a3-fa52-47b3-85ef-8baceff8d172",
                  "type":"PROCESSOR"
               },
               "zIndex":"0"
            }
         ],
         "processors":[
            {
               "id":"3fa515a3-fa52-47b3-85ef-8baceff8d172",
               "parentGroupId":"36fe07f4-72eb-43da-b86e-64277d3502e1",
               "position":{
                  "x":"95.92713597664039",
                  "y":"11.720025461581258"
               },
               "config":{
                  "bulletinLevel":"WARN",
                  "comments":"",
                  "concurrentlySchedulableTaskCount":"1",
                  "defaultConcurrentTasks":{
                     "entry":[
                        {
                           "key":"TIMER_DRIVEN",
                           "value":"1"
                        },
                        {
                           "key":"EVENT_DRIVEN",
                           "value":"0"
                        },
                        {
                           "key":"CRON_DRIVEN",
                           "value":"1"
                        }
                     ]
                  },
                  "defaultSchedulingPeriod":{
                     "entry":[
                        {
                           "key":"TIMER_DRIVEN",
                           "value":"0 sec"
                        },
                        {
                           "key":"CRON_DRIVEN",
                           "value":"* * * * * ?"
                        }
                     ]
                  },
                  "descriptors":{
                     "entry":[
                        {
                           "key":"Mongo URI",
                           "value":{
                              "description":"MongoURI, typically of the form: mongodb://host1[:port1][,host2[:port2],...]",
                              "displayName":"Mongo URI",
                              "dynamic":"false",
                              "name":"Mongo URI",
                              "required":"true",
                              "sensitive":"false",
                              "supportsEl":"false"
                           }
                        },
                        {
                           "key":"Mongo Database Name",
                           "value":{
                              "description":"The name of the database to use",
                              "displayName":"Mongo Database Name",
                              "dynamic":"false",
                              "name":"Mongo Database Name",
                              "required":"true",
                              "sensitive":"false",
                              "supportsEl":"false"
                           }
                        },
                        {
                           "key":"Mongo Collection Name",
                           "value":{
                              "description":"The name of the collection to use",
                              "displayName":"Mongo Collection Name",
                              "dynamic":"false",
                              "name":"Mongo Collection Name",
                              "required":"true",
                              "sensitive":"false",
                              "supportsEl":"false"
                           }
                        },
                        {
                           "key":"Mode",
                           "value":{
                              "allowableValues":[
                                 {
                                    "displayName":"insert",
                                    "value":"insert"
                                 },
                                 {
                                    "displayName":"update",
                                    "value":"update"
                                 }
                              ],
                              "defaultValue":"insert",
                              "description":"Indicates whether the processor should insert or update content",
                              "displayName":"Mode",
                              "dynamic":"false",
                              "name":"Mode",
                              "required":"true",
                              "sensitive":"false",
                              "supportsEl":"false"
                           }
                        },
                        {
                           "key":"Upsert",
                           "value":{
                              "allowableValues":[
                                 {
                                    "displayName":"true",
                                    "value":"true"
                                 },
                                 {
                                    "displayName":"false",
                                    "value":"false"
                                 }
                              ],
                              "defaultValue":"false",
                              "description":"When true, inserts a document if no document matches the update query criteria; this property is valid only when using update mode, otherwise it is ignored",
                              "displayName":"Upsert",
                              "dynamic":"false",
                              "name":"Upsert",
                              "required":"true",
                              "sensitive":"false",
                              "supportsEl":"false"
                           }
                        },
                        {
                           "key":"Update Query Key",
                           "value":{
                              "defaultValue":"_id",
                              "description":"Key name used to build the update query criteria; this property is valid only when using update mode, otherwise it is ignored",
                              "displayName":"Update Query Key",
                              "dynamic":"false",
                              "name":"Update Query Key",
                              "required":"true",
                              "sensitive":"false",
                              "supportsEl":"false"
                           }
                        },
                        {
                           "key":"Write Concern",
                           "value":{
                              "allowableValues":[
                                 {
                                    "displayName":"ACKNOWLEDGED",
                                    "value":"ACKNOWLEDGED"
                                 },
                                 {
                                    "displayName":"UNACKNOWLEDGED",
                                    "value":"UNACKNOWLEDGED"
                                 },
                                 {
                                    "displayName":"FSYNCED",
                                    "value":"FSYNCED"
                                 },
                                 {
                                    "displayName":"JOURNALED",
                                    "value":"JOURNALED"
                                 },
                                 {
                                    "displayName":"REPLICA_ACKNOWLEDGED",
                                    "value":"REPLICA_ACKNOWLEDGED"
                                 },
                                 {
                                    "displayName":"MAJORITY",
                                    "value":"MAJORITY"
                                 }
                              ],
                              "defaultValue":"ACKNOWLEDGED",
                              "description":"The write concern to use",
                              "displayName":"Write Concern",
                              "dynamic":"false",
                              "name":"Write Concern",
                              "required":"true",
                              "sensitive":"false",
                              "supportsEl":"false"
                           }
                        },
                        {
                           "key":"Character Set",
                           "value":{
                              "defaultValue":"UTF-8",
                              "description":"The Character Set in which the data is encoded",
                              "displayName":"Character Set",
                              "dynamic":"false",
                              "name":"Character Set",
                              "required":"true",
                              "sensitive":"false",
                              "supportsEl":"false"
                           }
                        }
                     ]
                  },
                  "lossTolerant":"false",
                  "penaltyDuration":"30 sec",
                  "properties":{
                     "entry":[
                        {
                           "key":"Mongo URI",
                           "value":"mongodb://localhost:27017/"
                        },
                        {
                           "key":"Mongo Database Name",
                           "value":"test"
                        },
                        {
                           "key":"Mongo Collection Name",
                           "value":"restaurants"
                        },
                        {
                           "key":"Mode"
                        },
                        {
                           "key":"Upsert"
                        },
                        {
                           "key":"Update Query Key"
                        },
                        {
                           "key":"Write Concern"
                        },
                        {
                           "key":"Character Set"
                        }
                     ]
                  },
                  "runDurationMillis":"0",
                  "schedulingPeriod":"0 sec",
                  "schedulingStrategy":"TIMER_DRIVEN",
                  "yieldDuration":"1 sec"
               },
               "name":"PutMongo",
               "relationships":[
                  {
                     "autoTerminate":"false",
                     "description":"All FlowFiles that cannot be written to MongoDB are routed to this relationship",
                     "name":"failure"
                  },
                  {
                     "autoTerminate":"false",
                     "description":"All FlowFiles that are written to MongoDB are routed to this relationship",
                     "name":"success"
                  }
               ],
               "state":"STOPPED",
               "style":"",
               "supportsEventDriven":"true",
               "supportsParallelProcessing":"true",
               "type":"org.apache.nifi.processors.mongodb.PutMongo"
            },
            {
               "id":"41e56cba-c491-4681-bbff-3b789a2a47cd",
               "parentGroupId":"36fe07f4-72eb-43da-b86e-64277d3502e1",
               "position":{
                  "x":"328.2585312503618",
                  "y":"222.4069545913465"
               },
               "config":{
                  "bulletinLevel":"WARN",
                  "comments":"",
                  "concurrentlySchedulableTaskCount":"1",
                  "defaultConcurrentTasks":{
                     "entry":[
                        {
                           "key":"TIMER_DRIVEN",
                           "value":"1"
                        },
                        {
                           "key":"EVENT_DRIVEN",
                           "value":"0"
                        },
                        {
                           "key":"CRON_DRIVEN",
                           "value":"1"
                        }
                     ]
                  },
                  "defaultSchedulingPeriod":{
                     "entry":[
                        {
                           "key":"TIMER_DRIVEN",
                           "value":"0 sec"
                        },
                        {
                           "key":"CRON_DRIVEN",
                           "value":"* * * * * ?"
                        }
                     ]
                  },
                  "descriptors":{
                     "entry":{
                        "key":"Delete Attributes Expression",
                        "value":{
                           "description":"Regular expression for attributes to be deleted from flowfiles.",
                           "displayName":"Delete Attributes Expression",
                           "dynamic":"false",
                           "name":"Delete Attributes Expression",
                           "required":"false",
                           "sensitive":"false",
                           "supportsEl":"true"
                        }
                     }
                  },
                  "lossTolerant":"false",
                  "penaltyDuration":"30 sec",
                  "properties":{
                     "entry":{
                        "key":"Delete Attributes Expression"
                     }
                  },
                  "runDurationMillis":"0",
                  "schedulingPeriod":"0 sec",
                  "schedulingStrategy":"TIMER_DRIVEN",
                  "yieldDuration":"1 sec"
               },
               "name":"UpdateAttribute",
               "relationships":{
                  "autoTerminate":"true",
                  "description":"All FlowFiles are routed to this relationship",
                  "name":"success"
               },
               "state":"STOPPED",
               "style":"",
               "supportsEventDriven":"true",
               "supportsParallelProcessing":"true",
               "type":"org.apache.nifi.processors.attributes.UpdateAttribute"
            },
            {
               "id":"fe80dab5-e13f-4af2-a9d3-507952a7516c",
               "parentGroupId":"36fe07f4-72eb-43da-b86e-64277d3502e1",
               "position":{
                  "x":"848.8032395023149",
                  "y":"223.48411828763557"
               },
               "config":{
                  "bulletinLevel":"WARN",
                  "comments":"",
                  "concurrentlySchedulableTaskCount":"1",
                  "defaultConcurrentTasks":{
                     "entry":[
                        {
                           "key":"TIMER_DRIVEN",
                           "value":"1"
                        },
                        {
                           "key":"EVENT_DRIVEN",
                           "value":"0"
                        },
                        {
                           "key":"CRON_DRIVEN",
                           "value":"1"
                        }
                     ]
                  },
                  "defaultSchedulingPeriod":{
                     "entry":[
                        {
                           "key":"TIMER_DRIVEN",
                           "value":"0 sec"
                        },
                        {
                           "key":"CRON_DRIVEN",
                           "value":"* * * * * ?"
                        }
                     ]
                  },
                  "descriptors":{
                     "entry":{
                        "key":"Delete Attributes Expression",
                        "value":{
                           "description":"Regular expression for attributes to be deleted from flowfiles.",
                           "displayName":"Delete Attributes Expression",
                           "dynamic":"false",
                           "name":"Delete Attributes Expression",
                           "required":"false",
                           "sensitive":"false",
                           "supportsEl":"true"
                        }
                     }
                  },
                  "lossTolerant":"false",
                  "penaltyDuration":"30 sec",
                  "properties":{
                     "entry":{
                        "key":"Delete Attributes Expression"
                     }
                  },
                  "runDurationMillis":"0",
                  "schedulingPeriod":"0 sec",
                  "schedulingStrategy":"TIMER_DRIVEN",
                  "yieldDuration":"1 sec"
               },
               "name":"UpdateAttribute",
               "relationships":{
                  "autoTerminate":"true",
                  "description":"All FlowFiles are routed to this relationship",
                  "name":"success"
               },
               "state":"STOPPED",
               "style":"",
               "supportsEventDriven":"true",
               "supportsParallelProcessing":"true",
               "type":"org.apache.nifi.processors.attributes.UpdateAttribute"
            },
            {
               "id":"50706ba6-a16f-4efa-91cd-5faacf3590d5",
               "parentGroupId":"36fe07f4-72eb-43da-b86e-64277d3502e1",
               "position":{
                  "x":"843.2312262690032",
                  "y":"-0.8109729176555049"
               },
               "config":{
                  "bulletinLevel":"WARN",
                  "comments":"",
                  "concurrentlySchedulableTaskCount":"1",
                  "defaultConcurrentTasks":{
                     "entry":[
                        {
                           "key":"TIMER_DRIVEN",
                           "value":"1"
                        },
                        {
                           "key":"EVENT_DRIVEN",
                           "value":"0"
                        },
                        {
                           "key":"CRON_DRIVEN",
                           "value":"1"
                        }
                     ]
                  },
                  "defaultSchedulingPeriod":{
                     "entry":[
                        {
                           "key":"TIMER_DRIVEN",
                           "value":"0 sec"
                        },
                        {
                           "key":"CRON_DRIVEN",
                           "value":"* * * * * ?"
                        }
                     ]
                  },
                  "descriptors":{
                     "entry":[
                        {
                           "key":"Mongo URI",
                           "value":{
                              "description":"MongoURI, typically of the form: mongodb://host1[:port1][,host2[:port2],...]",
                              "displayName":"Mongo URI",
                              "dynamic":"false",
                              "name":"Mongo URI",
                              "required":"true",
                              "sensitive":"false",
                              "supportsEl":"false"
                           }
                        },
                        {
                           "key":"Mongo Database Name",
                           "value":{
                              "description":"The name of the database to use",
                              "displayName":"Mongo Database Name",
                              "dynamic":"false",
                              "name":"Mongo Database Name",
                              "required":"true",
                              "sensitive":"false",
                              "supportsEl":"false"
                           }
                        },
                        {
                           "key":"Mongo Collection Name",
                           "value":{
                              "description":"The name of the collection to use",
                              "displayName":"Mongo Collection Name",
                              "dynamic":"false",
                              "name":"Mongo Collection Name",
                              "required":"true",
                              "sensitive":"false",
                              "supportsEl":"false"
                           }
                        },
                        {
                           "key":"Query",
                           "value":{
                              "description":"The selection criteria; must be a valid BSON document; if omitted the entire collection will be queried",
                              "displayName":"Query",
                              "dynamic":"false",
                              "name":"Query",
                              "required":"false",
                              "sensitive":"false",
                              "supportsEl":"false"
                           }
                        },
                        {
                           "key":"Projection",
                           "value":{
                              "description":"The fields to be returned from the documents in the result set; must be a valid BSON document",
                              "displayName":"Projection",
                              "dynamic":"false",
                              "name":"Projection",
                              "required":"false",
                              "sensitive":"false",
                              "supportsEl":"false"
                           }
                        },
                        {
                           "key":"Sort",
                           "value":{
                              "description":"The fields by which to sort; must be a valid BSON document",
                              "displayName":"Sort",
                              "dynamic":"false",
                              "name":"Sort",
                              "required":"false",
                              "sensitive":"false",
                              "supportsEl":"false"
                           }
                        },
                        {
                           "key":"Limit",
                           "value":{
                              "description":"The maximum number of elements to return",
                              "displayName":"Limit",
                              "dynamic":"false",
                              "name":"Limit",
                              "required":"false",
                              "sensitive":"false",
                              "supportsEl":"false"
                           }
                        },
                        {
                           "key":"Batch Size",
                           "value":{
                              "description":"The number of elements returned from the server in one batch",
                              "displayName":"Batch Size",
                              "dynamic":"false",
                              "name":"Batch Size",
                              "required":"false",
                              "sensitive":"false",
                              "supportsEl":"false"
                           }
                        }
                     ]
                  },
                  "lossTolerant":"false",
                  "penaltyDuration":"30 sec",
                  "properties":{
                     "entry":[
                        {
                           "key":"Mongo URI",
                           "value":"mongodb://localhost:27017/"
                        },
                        {
                           "key":"Mongo Database Name",
                           "value":"test"
                        },
                        {
                           "key":"Mongo Collection Name",
                           "value":"restaurants"
                        },
                        {
                           "key":"Query",
                           "value":"{\"restaurant_id\":\"8765309\"}"
                        },
                        {
                           "key":"Projection"
                        },
                        {
                           "key":"Sort"
                        },
                        {
                           "key":"Limit"
                        },
                        {
                           "key":"Batch Size"
                        }
                     ]
                  },
                  "runDurationMillis":"0",
                  "schedulingPeriod":"10 sec",
                  "schedulingStrategy":"TIMER_DRIVEN",
                  "yieldDuration":"1 sec"
               },
               "name":"GetMongo",
               "relationships":{
                  "autoTerminate":"false",
                  "description":"All files are routed to success",
                  "name":"success"
               },
               "state":"STOPPED",
               "style":"",
               "supportsEventDriven":"false",
               "supportsParallelProcessing":"true",
               "type":"org.apache.nifi.processors.mongodb.GetMongo"
            },
            {
               "id":"c6251f06-f526-4f07-abfb-9f5e62a8f38b",
               "parentGroupId":"36fe07f4-72eb-43da-b86e-64277d3502e1",
               "position":{
                  "x":"84.92584228515625",
                  "y":"-397.9516686499119"
               },
               "config":{
                  "bulletinLevel":"WARN",
                  "comments":"",
                  "concurrentlySchedulableTaskCount":"1",
                  "defaultConcurrentTasks":{
                     "entry":[
                        {
                           "key":"TIMER_DRIVEN",
                           "value":"1"
                        },
                        {
                           "key":"EVENT_DRIVEN",
                           "value":"0"
                        },
                        {
                           "key":"CRON_DRIVEN",
                           "value":"1"
                        }
                     ]
                  },
                  "defaultSchedulingPeriod":{
                     "entry":[
                        {
                           "key":"TIMER_DRIVEN",
                           "value":"0 sec"
                        },
                        {
                           "key":"CRON_DRIVEN",
                           "value":"* * * * * ?"
                        }
                     ]
                  },
                  "descriptors":{
                     "entry":[
                        {
                           "key":"File Size",
                           "value":{
                              "description":"The size of the file that will be used",
                              "displayName":"File Size",
                              "dynamic":"false",
                              "name":"File Size",
                              "required":"true",
                              "sensitive":"false",
                              "supportsEl":"false"
                           }
                        },
                        {
                           "key":"Batch Size",
                           "value":{
                              "defaultValue":"1",
                              "description":"The number of FlowFiles to be transferred in each invocation",
                              "displayName":"Batch Size",
                              "dynamic":"false",
                              "name":"Batch Size",
                              "required":"true",
                              "sensitive":"false",
                              "supportsEl":"false"
                           }
                        },
                        {
                           "key":"Data Format",
                           "value":{
                              "allowableValues":[
                                 {
                                    "displayName":"Binary",
                                    "value":"Binary"
                                 },
                                 {
                                    "displayName":"Text",
                                    "value":"Text"
                                 }
                              ],
                              "defaultValue":"Binary",
                              "description":"Specifies whether the data should be Text or Binary",
                              "displayName":"Data Format",
                              "dynamic":"false",
                              "name":"Data Format",
                              "required":"true",
                              "sensitive":"false",
                              "supportsEl":"false"
                           }
                        },
                        {
                           "key":"Unique FlowFiles",
                           "value":{
                              "allowableValues":[
                                 {
                                    "displayName":"true",
                                    "value":"true"
                                 },
                                 {
                                    "displayName":"false",
                                    "value":"false"
                                 }
                              ],
                              "defaultValue":"false",
                              "description":"If true, each FlowFile that is generated will be unique. If false, a random value will be generated and all FlowFiles will get the same content but this offers much higher throughput",
                              "displayName":"Unique FlowFiles",
                              "dynamic":"false",
                              "name":"Unique FlowFiles",
                              "required":"true",
                              "sensitive":"false",
                              "supportsEl":"false"
                           }
                        }
                     ]
                  },
                  "lossTolerant":"false",
                  "penaltyDuration":"30 sec",
                  "properties":{
                     "entry":[
                        {
                           "key":"File Size",
                           "value":"3b"
                        },
                        {
                           "key":"Batch Size",
                           "value":"1"
                        },
                        {
                           "key":"Data Format",
                           "value":"Text"
                        },
                        {
                           "key":"Unique FlowFiles",
                           "value":"true"
                        }
                     ]
                  },
                  "runDurationMillis":"0",
                  "schedulingPeriod":"10 sec",
                  "schedulingStrategy":"TIMER_DRIVEN",
                  "yieldDuration":"1 sec"
               },
               "name":"GenerateFlowFile",
               "relationships":{
                  "autoTerminate":"false",
                  "description":"",
                  "name":"success"
               },
               "state":"STOPPED",
               "style":"",
               "supportsEventDriven":"false",
               "supportsParallelProcessing":"true",
               "type":"org.apache.nifi.processors.standard.GenerateFlowFile"
            },
            {
               "id":"cf620c13-da2e-4a58-9f3f-03540ec4e4a8",
               "parentGroupId":"36fe07f4-72eb-43da-b86e-64277d3502e1",
               "position":{
                  "x":"-62.41930993616168",
                  "y":"222.46898156888557"
               },
               "config":{
                  "bulletinLevel":"WARN",
                  "comments":"",
                  "concurrentlySchedulableTaskCount":"1",
                  "defaultConcurrentTasks":{
                     "entry":[
                        {
                           "key":"TIMER_DRIVEN",
                           "value":"1"
                        },
                        {
                           "key":"EVENT_DRIVEN",
                           "value":"0"
                        },
                        {
                           "key":"CRON_DRIVEN",
                           "value":"1"
                        }
                     ]
                  },
                  "defaultSchedulingPeriod":{
                     "entry":[
                        {
                           "key":"TIMER_DRIVEN",
                           "value":"0 sec"
                        },
                        {
                           "key":"CRON_DRIVEN",
                           "value":"* * * * * ?"
                        }
                     ]
                  },
                  "descriptors":{
                     "entry":{
                        "key":"Delete Attributes Expression",
                        "value":{
                           "description":"Regular expression for attributes to be deleted from flowfiles.",
                           "displayName":"Delete Attributes Expression",
                           "dynamic":"false",
                           "name":"Delete Attributes Expression",
                           "required":"false",
                           "sensitive":"false",
                           "supportsEl":"true"
                        }
                     }
                  },
                  "lossTolerant":"false",
                  "penaltyDuration":"30 sec",
                  "properties":{
                     "entry":{
                        "key":"Delete Attributes Expression"
                     }
                  },
                  "runDurationMillis":"0",
                  "schedulingPeriod":"0 sec",
                  "schedulingStrategy":"TIMER_DRIVEN",
                  "yieldDuration":"1 sec"
               },
               "name":"UpdateAttribute",
               "relationships":{
                  "autoTerminate":"true",
                  "description":"All FlowFiles are routed to this relationship",
                  "name":"success"
               },
               "state":"STOPPED",
               "style":"",
               "supportsEventDriven":"true",
               "supportsParallelProcessing":"true",
               "type":"org.apache.nifi.processors.attributes.UpdateAttribute"
            },
            {
               "id":"89707d29-fd48-4fb4-8a28-a3b7c38af969",
               "parentGroupId":"36fe07f4-72eb-43da-b86e-64277d3502e1",
               "position":{
                  "x":"91.37043034776332",
                  "y":"-197.889671006487"
               },
               "config":{
                  "bulletinLevel":"WARN",
                  "comments":"",
                  "concurrentlySchedulableTaskCount":"1",
                  "defaultConcurrentTasks":{
                     "entry":[
                        {
                           "key":"TIMER_DRIVEN",
                           "value":"1"
                        },
                        {
                           "key":"EVENT_DRIVEN",
                           "value":"0"
                        },
                        {
                           "key":"CRON_DRIVEN",
                           "value":"1"
                        }
                     ]
                  },
                  "defaultSchedulingPeriod":{
                     "entry":[
                        {
                           "key":"TIMER_DRIVEN",
                           "value":"0 sec"
                        },
                        {
                           "key":"CRON_DRIVEN",
                           "value":"* * * * * ?"
                        }
                     ]
                  },
                  "descriptors":{
                     "entry":[
                        {
                           "key":"Regular Expression",
                           "value":{
                              "defaultValue":"(?s:^.*$)",
                              "description":"The Search Value to search for in the FlowFile content. Only used for 'Literal Replace' and 'Regex Replace' matching strategies",
                              "displayName":"Search Value",
                              "dynamic":"false",
                              "name":"Regular Expression",
                              "required":"true",
                              "sensitive":"false",
                              "supportsEl":"true"
                           }
                        },
                        {
                           "key":"Replacement Value",
                           "value":{
                              "defaultValue":"$1",
                              "description":"The value to insert using the 'Replacement Strategy'. Using \"Regex Replace\" back-references to Regular Expression capturing groups are supported, but back-references that reference capturing groups that do not exist in the regular expression will be treated as literal value. Back References may also be referenced using the Expression Language, as '$1', '$2', etc. The single-tick marks MUST be included, as these variables are not \"Standard\" attribute names (attribute names must be quoted unless they contain only numbers, letters, and _).",
                              "displayName":"Replacement Value",
                              "dynamic":"false",
                              "name":"Replacement Value",
                              "required":"true",
                              "sensitive":"false",
                              "supportsEl":"true"
                           }
                        },
                        {
                           "key":"Character Set",
                           "value":{
                              "defaultValue":"UTF-8",
                              "description":"The Character Set in which the file is encoded",
                              "displayName":"Character Set",
                              "dynamic":"false",
                              "name":"Character Set",
                              "required":"true",
                              "sensitive":"false",
                              "supportsEl":"false"
                           }
                        },
                        {
                           "key":"Maximum Buffer Size",
                           "value":{
                              "defaultValue":"1 MB",
                              "description":"Specifies the maximum amount of data to buffer (per file or per line, depending on the Evaluation Mode) in order to apply the replacement. If 'Entire Text' (in Evaluation Mode) is selected and the FlowFile is larger than this value, the FlowFile will be routed to 'failure'. In 'Line-by-Line' Mode, if a single line is larger than this value, the FlowFile will be routed to 'failure'. A default value of 1 MB is provided, primarily for 'Entire Text' mode. In 'Line-by-Line' Mode, a value such as 8 KB or 16 KB is suggested. This value is ignored if the <Replacement Strategy> property is set to one of: Append, Prepend, Always Replace",
                              "displayName":"Maximum Buffer Size",
                              "dynamic":"false",
                              "name":"Maximum Buffer Size",
                              "required":"true",
                              "sensitive":"false",
                              "supportsEl":"false"
                           }
                        },
                        {
                           "key":"Replacement Strategy",
                           "value":{
                              "allowableValues":[
                                 {
                                    "description":"Insert the Replacement Value at the beginning of the FlowFile or the beginning of each line (depending on the Evaluation Mode). For \"Line-by-Line\" Evaluation Mode, the value will be prepended to each line. For \"Entire Text\" evaluation mode, the value will be prepended to the entire text.",
                                    "displayName":"Prepend",
                                    "value":"Prepend"
                                 },
                                 {
                                    "description":"Insert the Replacement Value at the end of the FlowFile or the end of each line (depending on the Evluation Mode). For \"Line-by-Line\" Evaluation Mode, the value will be appended to each line. For \"Entire Text\" evaluation mode, the value will be appended to the entire text.",
                                    "displayName":"Append",
                                    "value":"Append"
                                 },
                                 {
                                    "description":"Interpret the Search Value as a Regular Expression and replace all matches with the Replacement Value. The Replacement Value may reference Capturing Groups used in the Search Value by using a dollar-sign followed by the Capturing Group number, such as $1 or $2. If the Search Value is set to .* then everything is replaced without even evaluating the Regular Expression.",
                                    "displayName":"Regex Replace",
                                    "value":"Regex Replace"
                                 },
                                 {
                                    "description":"Search for all instances of the Search Value and replace the matches with the Replacement Value.",
                                    "displayName":"Literal Replace",
                                    "value":"Literal Replace"
                                 },
                                 {
                                    "description":"Always replaces the entire line or the entire contents of the FlowFile (depending on the value of the <Evaluation Mode> property) and does not bother searching for any value. When this strategy is chosen, the <Search Value> property is ignored.",
                                    "displayName":"Always Replace",
                                    "value":"Always Replace"
                                 }
                              ],
                              "defaultValue":"Regex Replace",
                              "description":"The strategy for how and what to replace within the FlowFile's text content.",
                              "displayName":"Replacement Strategy",
                              "dynamic":"false",
                              "name":"Replacement Strategy",
                              "required":"true",
                              "sensitive":"false",
                              "supportsEl":"false"
                           }
                        },
                        {
                           "key":"Evaluation Mode",
                           "value":{
                              "allowableValues":[
                                 {
                                    "displayName":"Line-by-Line",
                                    "value":"Line-by-Line"
                                 },
                                 {
                                    "displayName":"Entire text",
                                    "value":"Entire text"
                                 }
                              ],
                              "defaultValue":"Entire text",
                              "description":"Run the 'Replacement Strategy' against each line separately (Line-by-Line) or buffer the entire file into memory (Entire Text) and run against that.",
                              "displayName":"Evaluation Mode",
                              "dynamic":"false",
                              "name":"Evaluation Mode",
                              "required":"true",
                              "sensitive":"false",
                              "supportsEl":"false"
                           }
                        }
                     ]
                  },
                  "lossTolerant":"false",
                  "penaltyDuration":"30 sec",
                  "properties":{
                     "entry":[
                        {
                           "key":"Regular Expression"
                        },
                        {
                           "key":"Replacement Value",
                           "value":"{\"address\": {\"building\": \"1007\", \"coord\": [-73.856077, 40.848447], \"street\": \"Morris Park Ave\", \"zipcode\": \"10462\"}, \"borough\": \"Bronx\", \"cuisine\": \"Bakery\", \"grades\": [{\"date\": {\"$date\": 1393804800000}, \"grade\": \"A\", \"score\": 2}, {\"date\": {\"$date\": 1378857600000}, \"grade\": \"A\", \"score\": 6}, {\"date\": {\"$date\": 1358985600000}, \"grade\": \"A\", \"score\": 10}, {\"date\": {\"$date\": 1322006400000}, \"grade\": \"A\", \"score\": 9}, {\"date\": {\"$date\": 1299715200000}, \"grade\": \"B\", \"score\": 14}], \"name\": \"NiFi Test Shop\", \"restaurant_id\": \"8765309\"}"
                        },
                        {
                           "key":"Character Set"
                        },
                        {
                           "key":"Maximum Buffer Size"
                        },
                        {
                           "key":"Replacement Strategy"
                        },
                        {
                           "key":"Evaluation Mode"
                        }
                     ]
                  },
                  "runDurationMillis":"0",
                  "schedulingPeriod":"0 sec",
                  "schedulingStrategy":"TIMER_DRIVEN",
                  "yieldDuration":"1 sec"
               },
               "name":"ReplaceText",
               "relationships":[
                  {
                     "autoTerminate":"true",
                     "description":"FlowFiles that could not be updated are routed to this relationship",
                     "name":"failure"
                  },
                  {
                     "autoTerminate":"false",
                     "description":"FlowFiles that have been successfully processed are routed to this relationship. This includes both FlowFiles that had text replaced and those that did not.",
                     "name":"success"
                  }
               ],
               "state":"STOPPED",
               "style":"",
               "supportsEventDriven":"true",
               "supportsParallelProcessing":"true",
               "type":"org.apache.nifi.processors.standard.ReplaceText"
            }
         ]
      },
      "timestamp":"01/13/2020 18:06:01 EST"
   }
}